dknorway/__init__.py
dknorway/admin.py
dknorway/apps.py
dknorway/models.py
dknorway/postnrcache.py
dknorway/jobs/__init__.py
dknorway/jobs/monthly/__init__.py
dknorway/jobs/monthly/posten_postnrimport.py
dknorway/migrations/0001_initial.py
dknorway/migrations/0002_auto_20181202_2348.py
dknorway/migrations/0003_auto_20200106_0933.py
dknorway/migrations/__init__.py
dknorway-0.1.5.dist-info/LICENSE
dknorway-0.1.5.dist-info/METADATA
dknorway-0.1.5.dist-info/WHEEL
dknorway-0.1.5.dist-info/top_level.txt
dknorway-0.1.5.dist-info/RECORD
