Metadata-Version: 2.1
Name: dknorway
Version: 0.1.5
Summary: dknorway - Models to hold Fylke, Kommune and PostSted + import script of file from Bring (Posten).
Home-page: https://github.com/datakortet/dknorway
Maintainer: Bjorn Pettersen
Maintainer-email: bp@datakortet.no
Classifier: Development Status :: 3 - Alpha
Classifier: Intended Audience :: Developers
Classifier: Programming Language :: Python
Classifier: Programming Language :: Python :: 3
Classifier: Topic :: Software Development :: Libraries
License-File: LICENSE
Requires-Dist: Django
Requires-Dist: requests
Requires-Dist: django-extensions (==2.1.0)
